pyidd/__init__.py
pyidd/main.py
pyidd-0.3.1.dist-info/LICENSE
pyidd-0.3.1.dist-info/METADATA
pyidd-0.3.1.dist-info/WHEEL
pyidd-0.3.1.dist-info/top_level.txt
pyidd-0.3.1.dist-info/RECORD
