Metadata-Version: 2.1
Name: pyidd
Version: 0.3.1
Summary: Identify the Distribution of Data
Home-page: https://github.com/MasoudKaviani/pyidd
Author: Masoud Kaviani
Author-email: kaviani.masoud@gmail.com
License: MIT
License-File: LICENSE
Requires-Dist: numpy
Requires-Dist: pandas
Requires-Dist: scipy
Requires-Dist: matplotlib
